caiyun_tr/__init__.py
caiyun_tr/__main__.py
caiyun_tr/caiyun_tr.py
caiyun_tr-0.1.1.dist-info/entry_points.txt
caiyun_tr-0.1.1.dist-info/LICENSE
caiyun_tr-0.1.1.dist-info/WHEEL
caiyun_tr-0.1.1.dist-info/METADATA
caiyun_tr-0.1.1.dist-info/RECORD
